pygidsim/__init__.py
pygidsim/directions.py
pygidsim/experiment.py
pygidsim/export_database.py
pygidsim/giwaxs_sim.py
pygidsim/int_sim.py
pygidsim/q_sim.py
pygidsim/data/__init__.py
pygidsim/data/atoms.py
pygidsim-0.1.1.data/data/__init__.py
pygidsim-0.1.1.data/data/atomic_scattering_params.json
pygidsim-0.1.1.data/data/atoms.py
pygidsim-0.1.1.dist-info/licenses/LICENSE
tests/__init__.py
tests/conftest.py
tests/test_cif.py
tests/test_crystal.py
tests/test_sglattice.py
pygidsim-0.1.1.dist-info/METADATA
pygidsim-0.1.1.dist-info/WHEEL
pygidsim-0.1.1.dist-info/top_level.txt
pygidsim-0.1.1.dist-info/RECORD
